{
  "updatedAt": "2026-05-06T13:15:56.273Z",
  "timezone": "Asia/Tokyo",
  "baselineMode": "previous_close",
  "baselineLabelJa": "前日終値",
  "source": "ig.com",
  "markets": [
    {
      "id": "weekend-us-tech-100-e1",
      "marketId": "SUNNAS",
      "name": "Weekend US Tech 100",
      "url": "https://www.ig.com/en/indices/markets-indices/weekend-us-tech-100-e1",
      "bid": 28284.8,
      "offer": 28319.8,
      "currentPrice": 28302.3,
      "high": 28531,
      "low": 28062.5,
      "stale": false,
      "fetchedAt": "2026-05-06T13:15:57.167Z",
      "baselineMode": "previous_close",
      "baselineLabelJa": "前日終値",
      "baselineTimezone": "America/New_York",
      "baselineCutoverHourLocal": 17,
      "baselineCutoverMinuteLocal": 0,
      "baselineCutoverLabelJa": "06:00/07:00 JST",
      "baselinePrice": 28106.4,
      "change": 195.9,
      "changePercent": 0.697,
      "baselineSource": "snapshot-close",
      "baselineSnapshotDate": "2026-05-05",
      "baselineSnapshotCapturedAt": "2026-05-05T20:46:25.388Z"
    },
    {
      "id": "weekend-wall-street",
      "marketId": "SUNDOW",
      "name": "Weekend Wall Street",
      "url": "https://www.ig.com/en/indices/markets-indices/weekend-wall-street",
      "bid": 49650.7,
      "offer": 49715.7,
      "currentPrice": 49683.2,
      "high": 49983.4,
      "low": 49207,
      "stale": false,
      "fetchedAt": "2026-05-06T13:15:56.860Z",
      "baselineMode": "previous_close",
      "baselineLabelJa": "前日終値",
      "baselineTimezone": "America/New_York",
      "baselineCutoverHourLocal": 17,
      "baselineCutoverMinuteLocal": 0,
      "baselineCutoverLabelJa": "06:00/07:00 JST",
      "baselinePrice": 49259.2,
      "change": 424,
      "changePercent": 0.8608,
      "baselineSource": "snapshot-close",
      "baselineSnapshotDate": "2026-05-05",
      "baselineSnapshotCapturedAt": "2026-05-05T20:46:25.388Z"
    },
    {
      "id": "weekend-uk-100",
      "marketId": "SUNFUN",
      "name": "Weekend UK 100",
      "url": "https://www.ig.com/en/indices/markets-indices/weekend-uk-100",
      "bid": 10431.8,
      "offer": 10443.8,
      "currentPrice": 10437.8,
      "high": 10494.8,
      "low": 10267.2,
      "stale": false,
      "fetchedAt": "2026-05-06T13:15:57.750Z",
      "baselineMode": "previous_close",
      "baselineLabelJa": "前日終値",
      "baselineTimezone": "America/New_York",
      "baselineCutoverHourLocal": 17,
      "baselineCutoverMinuteLocal": 0,
      "baselineCutoverLabelJa": "06:00/07:00 JST",
      "baselinePrice": 10277.7,
      "change": 160.1,
      "changePercent": 1.5577,
      "baselineSource": "snapshot-close",
      "baselineSnapshotDate": "2026-05-05",
      "baselineSnapshotCapturedAt": "2026-05-05T20:46:25.388Z"
    },
    {
      "id": "weekend-germany-40",
      "marketId": "SUNDAX",
      "name": "Weekend Germany 40",
      "url": "https://www.ig.com/en/indices/markets-indices/weekend-germany-40",
      "bid": 24870.2,
      "offer": 24905.2,
      "currentPrice": 24887.7,
      "high": 25167.2,
      "low": 24439,
      "stale": false,
      "fetchedAt": "2026-05-06T13:15:57.441Z",
      "baselineMode": "previous_close",
      "baselineLabelJa": "前日終値",
      "baselineTimezone": "America/New_York",
      "baselineCutoverHourLocal": 17,
      "baselineCutoverMinuteLocal": 0,
      "baselineCutoverLabelJa": "06:00/07:00 JST",
      "baselinePrice": 24465.4,
      "change": 422.3,
      "changePercent": 1.7261,
      "baselineSource": "snapshot-close",
      "baselineSnapshotDate": "2026-05-05",
      "baselineSnapshotCapturedAt": "2026-05-05T20:46:25.388Z"
    },
    {
      "id": "weekend-hongkong-hs50",
      "marketId": "SUNHANS",
      "name": "Weekend Hong Kong HS50",
      "url": "https://www.ig.com/en/indices/markets-indices/weekend-hongkong-hs50",
      "bid": 26299.2,
      "offer": 26374.2,
      "currentPrice": 26336.7,
      "high": 26521.9,
      "low": 25831.1,
      "stale": false,
      "fetchedAt": "2026-05-06T13:15:57.788Z",
      "baselineMode": "previous_close",
      "baselineLabelJa": "前日終値",
      "baselineTimezone": "America/New_York",
      "baselineCutoverHourLocal": 17,
      "baselineCutoverMinuteLocal": 0,
      "baselineCutoverLabelJa": "06:00/07:00 JST",
      "baselinePrice": 25931,
      "change": 405.7,
      "changePercent": 1.5645,
      "baselineSource": "snapshot-close",
      "baselineSnapshotDate": "2026-05-05",
      "baselineSnapshotCapturedAt": "2026-05-05T20:46:25.388Z"
    },
    {
      "id": "weekend-australia-200",
      "marketId": "SUNASX",
      "name": "Weekend Australia 200",
      "url": "https://www.ig.com/en/indices/markets-indices/weekend-australia-200",
      "bid": 8849,
      "offer": 8861,
      "currentPrice": 8855,
      "high": 8910.8,
      "low": 8699.8,
      "stale": false,
      "fetchedAt": "2026-05-06T13:15:57.756Z",
      "baselineMode": "previous_close",
      "baselineLabelJa": "前日終値",
      "baselineTimezone": "America/New_York",
      "baselineCutoverHourLocal": 17,
      "baselineCutoverMinuteLocal": 0,
      "baselineCutoverLabelJa": "06:00/07:00 JST",
      "baselinePrice": 8713.2,
      "change": 141.8,
      "changePercent": 1.6274,
      "baselineSource": "snapshot-close",
      "baselineSnapshotDate": "2026-05-05",
      "baselineSnapshotCapturedAt": "2026-05-05T20:46:25.388Z"
    },
    {
      "id": "weekend-gold",
      "marketId": "SUNGOLD",
      "name": "Weekend Gold",
      "url": "https://www.ig.com/en/indices/markets-indices/weekend-gold",
      "bid": 4667.6,
      "offer": 4682.6,
      "currentPrice": 4675.1,
      "high": 4729.5,
      "low": 4538.8,
      "stale": false,
      "fetchedAt": "2026-05-06T13:15:57.335Z",
      "baselineMode": "previous_close",
      "baselineLabelJa": "前日終値",
      "baselineTimezone": "America/New_York",
      "baselineCutoverHourLocal": 17,
      "baselineCutoverMinuteLocal": 0,
      "baselineCutoverLabelJa": "06:00/07:00 JST",
      "baselinePrice": 4558.3,
      "change": 116.8,
      "changePercent": 2.5624,
      "baselineSource": "snapshot-close",
      "baselineSnapshotDate": "2026-05-05",
      "baselineSnapshotCapturedAt": "2026-05-05T20:46:25.388Z"
    },
    {
      "id": "weekend-spot-silver",
      "marketId": "SUNSILVER",
      "name": "Weekend Spot Silver",
      "url": "https://www.ig.com/en/indices/markets-indices/weekend-spot-silver",
      "bid": 7643.7,
      "offer": 7668.7,
      "currentPrice": 7656.2,
      "high": 7794.1,
      "low": 7252.2,
      "stale": false,
      "fetchedAt": "2026-05-06T13:15:57.478Z",
      "baselineMode": "previous_close",
      "baselineLabelJa": "前日終値",
      "baselineTimezone": "America/New_York",
      "baselineCutoverHourLocal": 17,
      "baselineCutoverMinuteLocal": 0,
      "baselineCutoverLabelJa": "06:00/07:00 JST",
      "baselinePrice": 7283.5,
      "change": 372.7,
      "changePercent": 5.117,
      "baselineSource": "snapshot-close",
      "baselineSnapshotDate": "2026-05-05",
      "baselineSnapshotCapturedAt": "2026-05-05T20:46:25.388Z"
    },
    {
      "id": "weekend-oil---us-crude",
      "marketId": "SUNCL",
      "name": "Weekend Oil - US Crude",
      "url": "https://www.ig.com/en/indices/markets-indices/weekend-oil---us-crude",
      "bid": 9418.6,
      "offer": 9483.6,
      "currentPrice": 9451.1,
      "high": 10093.2,
      "low": 8695.2,
      "stale": false,
      "fetchedAt": "2026-05-06T13:15:56.987Z",
      "baselineMode": "previous_close",
      "baselineLabelJa": "前日終値",
      "baselineTimezone": "America/New_York",
      "baselineCutoverHourLocal": 17,
      "baselineCutoverMinuteLocal": 0,
      "baselineCutoverLabelJa": "06:00/07:00 JST",
      "baselinePrice": 10032.5,
      "change": -581.4,
      "changePercent": -5.7952,
      "baselineSource": "snapshot-close",
      "baselineSnapshotDate": "2026-05-05",
      "baselineSnapshotCapturedAt": "2026-05-05T20:46:25.388Z"
    },
    {
      "id": "weekend-usdjpy",
      "marketId": "SUNUSDJPY",
      "name": "Weekend USDJPY",
      "url": "https://www.ig.com/en/indices/markets-indices/weekend-usdjpy",
      "bid": 156.209,
      "offer": 156.369,
      "currentPrice": 156.289,
      "high": 158.015,
      "low": 154.954,
      "stale": false,
      "fetchedAt": "2026-05-06T13:15:57.792Z",
      "baselineMode": "previous_close",
      "baselineLabelJa": "前日終値",
      "baselineTimezone": "America/New_York",
      "baselineCutoverHourLocal": 17,
      "baselineCutoverMinuteLocal": 0,
      "baselineCutoverLabelJa": "06:00/07:00 JST",
      "baselinePrice": 157.88,
      "change": -1.591,
      "changePercent": -1.0077,
      "baselineSource": "snapshot-close",
      "baselineSnapshotDate": "2026-05-05",
      "baselineSnapshotCapturedAt": "2026-05-05T20:46:25.388Z"
    },
    {
      "id": "weekend-eurusd",
      "marketId": "SUNEURUSD",
      "name": "Weekend EURUSD",
      "url": "https://www.ig.com/en/indices/markets-indices/weekend-eurusd",
      "bid": 1.175,
      "offer": 1.1765,
      "currentPrice": 1.1757,
      "high": 1.1804,
      "low": 1.1684,
      "stale": false,
      "fetchedAt": "2026-05-06T13:15:57.432Z",
      "baselineMode": "previous_close",
      "baselineLabelJa": "前日終値",
      "baselineTimezone": "America/New_York",
      "baselineCutoverHourLocal": 17,
      "baselineCutoverMinuteLocal": 0,
      "baselineCutoverLabelJa": "06:00/07:00 JST",
      "baselinePrice": 1.1693,
      "change": 0.0064,
      "changePercent": 0.5473,
      "baselineSource": "snapshot-close",
      "baselineSnapshotDate": "2026-05-05",
      "baselineSnapshotCapturedAt": "2026-05-05T20:46:25.388Z"
    },
    {
      "id": "bitcoin-usd",
      "marketId": "BITCOIN",
      "name": "Bitcoin (USD)",
      "url": "https://www.ig.com/en/forex/markets-forex/bitcoin-1",
      "bid": 82024,
      "offer": 82069,
      "currentPrice": 82046.5,
      "high": 82892,
      "low": 80751,
      "stale": false,
      "fetchedAt": "2026-05-06T13:15:58.020Z",
      "baselineMode": "previous_close",
      "baselineLabelJa": "前日終値",
      "baselineTimezone": "America/New_York",
      "baselineCutoverHourLocal": 17,
      "baselineCutoverMinuteLocal": 0,
      "baselineCutoverLabelJa": "06:00/07:00 JST",
      "baselinePrice": 81585.5,
      "change": 461,
      "changePercent": 0.5651,
      "baselineSource": "snapshot-close",
      "baselineSnapshotDate": "2026-05-05",
      "baselineSnapshotCapturedAt": "2026-05-05T20:46:25.388Z"
    },
    {
      "id": "ether-usd",
      "marketId": "ETHUSD",
      "name": "Ether (USD)",
      "url": "https://www.ig.com/en/forex/markets-forex/ether-usd",
      "bid": 2394.3,
      "offer": 2395.7,
      "currentPrice": 2395,
      "high": 2423.9,
      "low": 2354.2,
      "stale": false,
      "fetchedAt": "2026-05-06T13:15:57.678Z",
      "baselineMode": "previous_close",
      "baselineLabelJa": "前日終値",
      "baselineTimezone": "America/New_York",
      "baselineCutoverHourLocal": 17,
      "baselineCutoverMinuteLocal": 0,
      "baselineCutoverLabelJa": "06:00/07:00 JST",
      "baselinePrice": 2380.8,
      "change": 14.2,
      "changePercent": 0.5964,
      "baselineSource": "snapshot-close",
      "baselineSnapshotDate": "2026-05-05",
      "baselineSnapshotCapturedAt": "2026-05-05T20:46:25.388Z"
    },
    {
      "id": "crypto-10-index",
      "marketId": "CRYPTOB10",
      "name": "Crypto 10 Index",
      "url": "https://www.ig.com/en/forex/markets-forex/crypto-10-index",
      "bid": 16043.65,
      "offer": 16123.65,
      "currentPrice": 16083.65,
      "high": 16246.4,
      "low": 15717.3,
      "stale": false,
      "fetchedAt": "2026-05-06T13:15:57.925Z",
      "baselineMode": "previous_close",
      "baselineLabelJa": "前日終値",
      "baselineTimezone": "America/New_York",
      "baselineCutoverHourLocal": 17,
      "baselineCutoverMinuteLocal": 0,
      "baselineCutoverLabelJa": "06:00/07:00 JST",
      "baselinePrice": 15886.52,
      "change": 197.13,
      "changePercent": 1.2409,
      "baselineSource": "snapshot-close",
      "baselineSnapshotDate": "2026-05-05",
      "baselineSnapshotCapturedAt": "2026-05-05T20:46:25.388Z"
    }
  ]
}
