{
  "updatedAt": "2026-04-02T23:30:30.607Z",
  "timezone": "Asia/Tokyo",
  "baselineMode": "previous_close",
  "baselineLabelJa": "前日終値",
  "source": "ig.com",
  "markets": [
    {
      "id": "weekend-us-tech-100-e1",
      "marketId": "SUNNAS",
      "name": "Weekend US Tech 100",
      "url": "https://www.ig.com/en/indices/markets-indices/weekend-us-tech-100-e1",
      "bid": 24009.9,
      "offer": 24044.9,
      "currentPrice": 24027.4,
      "high": 24061,
      "low": 23988.4,
      "stale": false,
      "fetchedAt": "2026-04-02T23:30:31.245Z",
      "baselineMode": "previous_close",
      "baselineLabelJa": "前日終値",
      "baselineTimezone": "America/New_York",
      "baselineCutoverHourLocal": 17,
      "baselineCutoverMinuteLocal": 0,
      "baselineCutoverLabelJa": "06:00/07:00 JST",
      "baselinePrice": 24035.8,
      "change": -8.4,
      "changePercent": -0.0349,
      "baselineSource": "snapshot-close",
      "baselineSnapshotDate": "2026-04-02",
      "baselineSnapshotCapturedAt": "2026-04-02T20:45:33.594Z"
    },
    {
      "id": "weekend-wall-street",
      "marketId": "SUNDOW",
      "name": "Weekend Wall Street",
      "url": "https://www.ig.com/en/indices/markets-indices/weekend-wall-street",
      "bid": 46477.8,
      "offer": 46542.8,
      "currentPrice": 46510.3,
      "high": 46560.3,
      "low": 46443.6,
      "stale": false,
      "fetchedAt": "2026-04-02T23:30:31.039Z",
      "baselineMode": "previous_close",
      "baselineLabelJa": "前日終値",
      "baselineTimezone": "America/New_York",
      "baselineCutoverHourLocal": 17,
      "baselineCutoverMinuteLocal": 0,
      "baselineCutoverLabelJa": "06:00/07:00 JST",
      "baselinePrice": 46519.2,
      "change": -8.9,
      "changePercent": -0.0191,
      "baselineSource": "snapshot-close",
      "baselineSnapshotDate": "2026-04-02",
      "baselineSnapshotCapturedAt": "2026-04-02T20:45:33.594Z"
    },
    {
      "id": "weekend-uk-100",
      "marketId": "SUNFUN",
      "name": "Weekend UK 100",
      "url": "https://www.ig.com/en/indices/markets-indices/weekend-uk-100",
      "bid": 10443.9,
      "offer": 10455.9,
      "currentPrice": 10449.9,
      "high": 10461,
      "low": 10441.8,
      "stale": false,
      "fetchedAt": "2026-04-02T23:30:31.847Z",
      "baselineMode": "previous_close",
      "baselineLabelJa": "前日終値",
      "baselineTimezone": "America/New_York",
      "baselineCutoverHourLocal": 17,
      "baselineCutoverMinuteLocal": 0,
      "baselineCutoverLabelJa": "06:00/07:00 JST",
      "baselinePrice": 10453.6,
      "change": -3.7,
      "changePercent": -0.0354,
      "baselineSource": "snapshot-close",
      "baselineSnapshotDate": "2026-04-02",
      "baselineSnapshotCapturedAt": "2026-04-02T20:45:33.594Z"
    },
    {
      "id": "weekend-germany-40",
      "marketId": "SUNDAX",
      "name": "Weekend Germany 40",
      "url": "https://www.ig.com/en/indices/markets-indices/weekend-germany-40",
      "bid": 23189.9,
      "offer": 23224.9,
      "currentPrice": 23207.4,
      "high": 23243.8,
      "low": 23176.7,
      "stale": false,
      "fetchedAt": "2026-04-02T23:30:32.350Z",
      "baselineMode": "previous_close",
      "baselineLabelJa": "前日終値",
      "baselineTimezone": "America/New_York",
      "baselineCutoverHourLocal": 17,
      "baselineCutoverMinuteLocal": 0,
      "baselineCutoverLabelJa": "06:00/07:00 JST",
      "baselinePrice": 23228.8,
      "change": -21.4,
      "changePercent": -0.0921,
      "baselineSource": "snapshot-close",
      "baselineSnapshotDate": "2026-04-02",
      "baselineSnapshotCapturedAt": "2026-04-02T20:45:33.594Z"
    },
    {
      "id": "weekend-hongkong-hs50",
      "marketId": "SUNHANS",
      "name": "Weekend Hong Kong HS50",
      "url": "https://www.ig.com/en/indices/markets-indices/weekend-hongkong-hs50",
      "bid": 25229.3,
      "offer": 25289.3,
      "currentPrice": 25259.3,
      "high": 25300,
      "low": 25218.3,
      "stale": false,
      "fetchedAt": "2026-04-02T23:30:32.259Z",
      "baselineMode": "previous_close",
      "baselineLabelJa": "前日終値",
      "baselineTimezone": "America/New_York",
      "baselineCutoverHourLocal": 17,
      "baselineCutoverMinuteLocal": 0,
      "baselineCutoverLabelJa": "06:00/07:00 JST",
      "baselinePrice": 25271.1,
      "change": -11.8,
      "changePercent": -0.0467,
      "baselineSource": "snapshot-close",
      "baselineSnapshotDate": "2026-04-02",
      "baselineSnapshotCapturedAt": "2026-04-02T20:45:33.594Z"
    },
    {
      "id": "weekend-australia-200",
      "marketId": "SUNASX",
      "name": "Weekend Australia 200",
      "url": "https://www.ig.com/en/indices/markets-indices/weekend-australia-200",
      "bid": 8625.9,
      "offer": 8637.9,
      "currentPrice": 8631.9,
      "high": 8639.7,
      "low": 8623.6,
      "stale": false,
      "fetchedAt": "2026-04-02T23:30:32.492Z",
      "baselineMode": "previous_close",
      "baselineLabelJa": "前日終値",
      "baselineTimezone": "America/New_York",
      "baselineCutoverHourLocal": 17,
      "baselineCutoverMinuteLocal": 0,
      "baselineCutoverLabelJa": "06:00/07:00 JST",
      "baselinePrice": 8632.4,
      "change": -0.5,
      "changePercent": -0.0058,
      "baselineSource": "snapshot-close",
      "baselineSnapshotDate": "2026-04-02",
      "baselineSnapshotCapturedAt": "2026-04-02T20:45:33.594Z"
    },
    {
      "id": "weekend-gold",
      "marketId": "SUNGOLD",
      "name": "Weekend Gold",
      "url": "https://www.ig.com/en/indices/markets-indices/weekend-gold",
      "bid": 4671.8,
      "offer": 4686.8,
      "currentPrice": 4679.3,
      "high": 4689.3,
      "low": 4654.1,
      "stale": false,
      "fetchedAt": "2026-04-02T23:30:31.286Z",
      "baselineMode": "previous_close",
      "baselineLabelJa": "前日終値",
      "baselineTimezone": "America/New_York",
      "baselineCutoverHourLocal": 17,
      "baselineCutoverMinuteLocal": 0,
      "baselineCutoverLabelJa": "06:00/07:00 JST",
      "baselinePrice": 4670.8,
      "change": 8.5,
      "changePercent": 0.182,
      "baselineSource": "snapshot-close",
      "baselineSnapshotDate": "2026-04-02",
      "baselineSnapshotCapturedAt": "2026-04-02T20:45:33.594Z"
    },
    {
      "id": "weekend-spot-silver",
      "marketId": "SUNSILVER",
      "name": "Weekend Spot Silver",
      "url": "https://www.ig.com/en/indices/markets-indices/weekend-spot-silver",
      "bid": 7286,
      "offer": 7311,
      "currentPrice": 7298.5,
      "high": 7317.5,
      "low": 7228,
      "stale": false,
      "fetchedAt": "2026-04-02T23:30:31.442Z",
      "baselineMode": "previous_close",
      "baselineLabelJa": "前日終値",
      "baselineTimezone": "America/New_York",
      "baselineCutoverHourLocal": 17,
      "baselineCutoverMinuteLocal": 0,
      "baselineCutoverLabelJa": "06:00/07:00 JST",
      "baselinePrice": 7286.1,
      "change": 12.4,
      "changePercent": 0.1702,
      "baselineSource": "snapshot-close",
      "baselineSnapshotDate": "2026-04-02",
      "baselineSnapshotCapturedAt": "2026-04-02T20:45:33.594Z"
    },
    {
      "id": "weekend-oil---us-crude",
      "marketId": "SUNCL",
      "name": "Weekend Oil - US Crude",
      "url": "https://www.ig.com/en/indices/markets-indices/weekend-oil---us-crude",
      "bid": 10551.2,
      "offer": 10611.2,
      "currentPrice": 10581.2,
      "high": 10617.2,
      "low": 10452.1,
      "stale": false,
      "fetchedAt": "2026-04-02T23:30:31.018Z",
      "baselineMode": "previous_close",
      "baselineLabelJa": "前日終値",
      "baselineTimezone": "America/New_York",
      "baselineCutoverHourLocal": 17,
      "baselineCutoverMinuteLocal": 0,
      "baselineCutoverLabelJa": "06:00/07:00 JST",
      "baselinePrice": 10559.9,
      "change": 21.3,
      "changePercent": 0.2017,
      "baselineSource": "snapshot-close",
      "baselineSnapshotDate": "2026-04-02",
      "baselineSnapshotCapturedAt": "2026-04-02T20:45:33.594Z"
    },
    {
      "id": "weekend-usdjpy",
      "marketId": "SUNUSDJPY",
      "name": "Weekend USDJPY",
      "url": "https://www.ig.com/en/indices/markets-indices/weekend-usdjpy",
      "bid": 159.44,
      "offer": 159.6,
      "currentPrice": 159.52,
      "high": 159.761,
      "low": 159.43,
      "stale": false,
      "fetchedAt": "2026-04-02T23:30:32.112Z",
      "baselineMode": "previous_close",
      "baselineLabelJa": "前日終値",
      "baselineTimezone": "America/New_York",
      "baselineCutoverHourLocal": 17,
      "baselineCutoverMinuteLocal": 0,
      "baselineCutoverLabelJa": "06:00/07:00 JST",
      "baselinePrice": 159.598,
      "change": -0.078,
      "changePercent": -0.0489,
      "baselineSource": "snapshot-close",
      "baselineSnapshotDate": "2026-04-02",
      "baselineSnapshotCapturedAt": "2026-04-02T20:45:33.594Z"
    },
    {
      "id": "weekend-eurusd",
      "marketId": "SUNEURUSD",
      "name": "Weekend EURUSD",
      "url": "https://www.ig.com/en/indices/markets-indices/weekend-eurusd",
      "bid": 1.1534,
      "offer": 1.1549,
      "currentPrice": 1.1542,
      "high": 1.1551,
      "low": 1.1525,
      "stale": false,
      "fetchedAt": "2026-04-02T23:30:32.486Z",
      "baselineMode": "previous_close",
      "baselineLabelJa": "前日終値",
      "baselineTimezone": "America/New_York",
      "baselineCutoverHourLocal": 17,
      "baselineCutoverMinuteLocal": 0,
      "baselineCutoverLabelJa": "06:00/07:00 JST",
      "baselinePrice": 1.1537,
      "change": 0.0005,
      "changePercent": 0.0433,
      "baselineSource": "snapshot-close",
      "baselineSnapshotDate": "2026-04-02",
      "baselineSnapshotCapturedAt": "2026-04-02T20:45:33.594Z"
    },
    {
      "id": "bitcoin-usd",
      "marketId": "BITCOIN",
      "name": "Bitcoin (USD)",
      "url": "https://www.ig.com/en/forex/markets-forex/bitcoin-1",
      "bid": 66960,
      "offer": 67005,
      "currentPrice": 66982.5,
      "high": 67138,
      "low": 66737,
      "stale": false,
      "fetchedAt": "2026-04-02T23:30:31.573Z",
      "baselineMode": "previous_close",
      "baselineLabelJa": "前日終値",
      "baselineTimezone": "America/New_York",
      "baselineCutoverHourLocal": 17,
      "baselineCutoverMinuteLocal": 0,
      "baselineCutoverLabelJa": "06:00/07:00 JST",
      "baselinePrice": 66999.5,
      "change": -17,
      "changePercent": -0.0254,
      "baselineSource": "snapshot-close",
      "baselineSnapshotDate": "2026-04-02",
      "baselineSnapshotCapturedAt": "2026-04-02T20:45:33.594Z"
    },
    {
      "id": "ether-usd",
      "marketId": "ETHUSD",
      "name": "Ether (USD)",
      "url": "https://www.ig.com/en/forex/markets-forex/ether-usd",
      "bid": 2056.9,
      "offer": 2058.3,
      "currentPrice": 2057.6,
      "high": 2071,
      "low": 2054.4,
      "stale": false,
      "fetchedAt": "2026-04-02T23:30:31.486Z",
      "baselineMode": "previous_close",
      "baselineLabelJa": "前日終値",
      "baselineTimezone": "America/New_York",
      "baselineCutoverHourLocal": 17,
      "baselineCutoverMinuteLocal": 0,
      "baselineCutoverLabelJa": "06:00/07:00 JST",
      "baselinePrice": 2071.2,
      "change": -13.6,
      "changePercent": -0.6566,
      "baselineSource": "snapshot-close",
      "baselineSnapshotDate": "2026-04-02",
      "baselineSnapshotCapturedAt": "2026-04-02T20:45:33.594Z"
    },
    {
      "id": "crypto-10-index",
      "marketId": "CRYPTOB10",
      "name": "Crypto 10 Index",
      "url": "https://www.ig.com/en/forex/markets-forex/crypto-10-index",
      "bid": 13856.15,
      "offer": 13936.15,
      "currentPrice": 13896.15,
      "high": 13974.5,
      "low": 13839.1,
      "stale": false,
      "fetchedAt": "2026-04-02T23:30:31.505Z",
      "baselineMode": "previous_close",
      "baselineLabelJa": "前日終値",
      "baselineTimezone": "America/New_York",
      "baselineCutoverHourLocal": 17,
      "baselineCutoverMinuteLocal": 0,
      "baselineCutoverLabelJa": "06:00/07:00 JST",
      "baselinePrice": 13939.16,
      "change": -43.01,
      "changePercent": -0.3086,
      "baselineSource": "snapshot-close",
      "baselineSnapshotDate": "2026-04-02",
      "baselineSnapshotCapturedAt": "2026-04-02T20:45:33.594Z"
    }
  ]
}
