{
  "updatedAt": "2026-03-27T17:46:11.917Z",
  "timezone": "Asia/Tokyo",
  "baselineMode": "previous_close",
  "baselineLabelJa": "前日終値",
  "source": "ig.com",
  "markets": [
    {
      "id": "weekend-us-tech-100-e1",
      "marketId": "SUNNAS",
      "name": "Weekend US Tech 100",
      "url": "https://www.ig.com/en/indices/markets-indices/weekend-us-tech-100-e1",
      "bid": 23186.1,
      "offer": 23221.1,
      "currentPrice": 23203.6,
      "high": 23799.9,
      "low": 23176.4,
      "stale": false,
      "fetchedAt": "2026-03-27T17:46:12.639Z",
      "baselineMode": "previous_close",
      "baselineLabelJa": "前日終値",
      "baselineTimezone": "America/New_York",
      "baselineCutoverHourLocal": 17,
      "baselineCutoverMinuteLocal": 0,
      "baselineCutoverLabelJa": "06:00/07:00 JST",
      "baselinePrice": 23664.2,
      "change": -460.6,
      "changePercent": -1.9464,
      "baselineSource": "snapshot-close",
      "baselineSnapshotDate": "2026-03-26",
      "baselineSnapshotCapturedAt": "2026-03-26T20:45:54.757Z"
    },
    {
      "id": "weekend-wall-street",
      "marketId": "SUNDOW",
      "name": "Weekend Wall Street",
      "url": "https://www.ig.com/en/indices/markets-indices/weekend-wall-street",
      "bid": 45345,
      "offer": 45410,
      "currentPrice": 45377.5,
      "high": 46278.9,
      "low": 45317.3,
      "stale": false,
      "fetchedAt": "2026-03-27T17:46:13.008Z",
      "baselineMode": "previous_close",
      "baselineLabelJa": "前日終値",
      "baselineTimezone": "America/New_York",
      "baselineCutoverHourLocal": 17,
      "baselineCutoverMinuteLocal": 0,
      "baselineCutoverLabelJa": "06:00/07:00 JST",
      "baselinePrice": 46128.8,
      "change": -751.3,
      "changePercent": -1.6287,
      "baselineSource": "snapshot-close",
      "baselineSnapshotDate": "2026-03-26",
      "baselineSnapshotCapturedAt": "2026-03-26T20:45:54.757Z"
    },
    {
      "id": "weekend-uk-100",
      "marketId": "SUNFUN",
      "name": "Weekend UK 100",
      "url": "https://www.ig.com/en/indices/markets-indices/weekend-uk-100",
      "bid": 9956.9,
      "offer": 9968.9,
      "currentPrice": 9962.9,
      "high": 10036.5,
      "low": 9875,
      "stale": false,
      "fetchedAt": "2026-03-27T17:46:13.482Z",
      "baselineMode": "previous_close",
      "baselineLabelJa": "前日終値",
      "baselineTimezone": "America/New_York",
      "baselineCutoverHourLocal": 17,
      "baselineCutoverMinuteLocal": 0,
      "baselineCutoverLabelJa": "06:00/07:00 JST",
      "baselinePrice": 9965.5,
      "change": -2.6,
      "changePercent": -0.0261,
      "baselineSource": "snapshot-close",
      "baselineSnapshotDate": "2026-03-26",
      "baselineSnapshotCapturedAt": "2026-03-26T20:45:54.757Z"
    },
    {
      "id": "weekend-germany-40",
      "marketId": "SUNDAX",
      "name": "Weekend Germany 40",
      "url": "https://www.ig.com/en/indices/markets-indices/weekend-germany-40",
      "bid": 22250.8,
      "offer": 22285.8,
      "currentPrice": 22268.3,
      "high": 22797.7,
      "low": 22189.8,
      "stale": false,
      "fetchedAt": "2026-03-27T17:46:13.467Z",
      "baselineMode": "previous_close",
      "baselineLabelJa": "前日終値",
      "baselineTimezone": "America/New_York",
      "baselineCutoverHourLocal": 17,
      "baselineCutoverMinuteLocal": 0,
      "baselineCutoverLabelJa": "06:00/07:00 JST",
      "baselinePrice": 22668.3,
      "change": -400,
      "changePercent": -1.7646,
      "baselineSource": "snapshot-close",
      "baselineSnapshotDate": "2026-03-26",
      "baselineSnapshotCapturedAt": "2026-03-26T20:45:54.757Z"
    },
    {
      "id": "weekend-hongkong-hs50",
      "marketId": "SUNHANS",
      "name": "Weekend Hong Kong HS50",
      "url": "https://www.ig.com/en/indices/markets-indices/weekend-hongkong-hs50",
      "bid": 24663.5,
      "offer": 24723.5,
      "currentPrice": 24693.5,
      "high": 25135.2,
      "low": 24637.6,
      "stale": false,
      "fetchedAt": "2026-03-27T17:46:13.408Z",
      "baselineMode": "previous_close",
      "baselineLabelJa": "前日終値",
      "baselineTimezone": "America/New_York",
      "baselineCutoverHourLocal": 17,
      "baselineCutoverMinuteLocal": 0,
      "baselineCutoverLabelJa": "06:00/07:00 JST",
      "baselinePrice": 24750.5,
      "change": -57,
      "changePercent": -0.2303,
      "baselineSource": "snapshot-close",
      "baselineSnapshotDate": "2026-03-26",
      "baselineSnapshotCapturedAt": "2026-03-26T20:45:54.757Z"
    },
    {
      "id": "weekend-australia-200",
      "marketId": "SUNASX",
      "name": "Weekend Australia 200",
      "url": "https://www.ig.com/en/indices/markets-indices/weekend-australia-200",
      "bid": 8432.9,
      "offer": 8442.9,
      "currentPrice": 8437.9,
      "high": 8524.6,
      "low": 8382.6,
      "stale": false,
      "fetchedAt": "2026-03-27T17:46:13.063Z",
      "baselineMode": "previous_close",
      "baselineLabelJa": "前日終値",
      "baselineTimezone": "America/New_York",
      "baselineCutoverHourLocal": 17,
      "baselineCutoverMinuteLocal": 0,
      "baselineCutoverLabelJa": "06:00/07:00 JST",
      "baselinePrice": 8446.9,
      "change": -9,
      "changePercent": -0.1065,
      "baselineSource": "snapshot-close",
      "baselineSnapshotDate": "2026-03-26",
      "baselineSnapshotCapturedAt": "2026-03-26T20:45:54.757Z"
    },
    {
      "id": "weekend-gold",
      "marketId": "SUNGOLD",
      "name": "Weekend Gold",
      "url": "https://www.ig.com/en/indices/markets-indices/weekend-gold",
      "bid": 4479.8,
      "offer": 4494.8,
      "currentPrice": 4487.3,
      "high": 4562.1,
      "low": 4343.8,
      "stale": false,
      "fetchedAt": "2026-03-27T17:46:13.383Z",
      "baselineMode": "previous_close",
      "baselineLabelJa": "前日終値",
      "baselineTimezone": "America/New_York",
      "baselineCutoverHourLocal": 17,
      "baselineCutoverMinuteLocal": 0,
      "baselineCutoverLabelJa": "06:00/07:00 JST",
      "baselinePrice": 4403,
      "change": 84.3,
      "changePercent": 1.9146,
      "baselineSource": "snapshot-close",
      "baselineSnapshotDate": "2026-03-26",
      "baselineSnapshotCapturedAt": "2026-03-26T20:45:54.757Z"
    },
    {
      "id": "weekend-spot-silver",
      "marketId": "SUNSILVER",
      "name": "Weekend Spot Silver",
      "url": "https://www.ig.com/en/indices/markets-indices/weekend-spot-silver",
      "bid": 6959.4,
      "offer": 6984.4,
      "currentPrice": 6971.9,
      "high": 7175.6,
      "low": 6692.6,
      "stale": false,
      "fetchedAt": "2026-03-27T17:46:13.118Z",
      "baselineMode": "previous_close",
      "baselineLabelJa": "前日終値",
      "baselineTimezone": "America/New_York",
      "baselineCutoverHourLocal": 17,
      "baselineCutoverMinuteLocal": 0,
      "baselineCutoverLabelJa": "06:00/07:00 JST",
      "baselinePrice": 6860.3,
      "change": 111.6,
      "changePercent": 1.6268,
      "baselineSource": "snapshot-close",
      "baselineSnapshotDate": "2026-03-26",
      "baselineSnapshotCapturedAt": "2026-03-26T20:45:54.757Z"
    },
    {
      "id": "weekend-oil---us-crude",
      "marketId": "SUNCL",
      "name": "Weekend Oil - US Crude",
      "url": "https://www.ig.com/en/indices/markets-indices/weekend-oil---us-crude",
      "bid": 9709.2,
      "offer": 9769.2,
      "currentPrice": 9739.2,
      "high": 9799.6,
      "low": 8879.7,
      "stale": false,
      "fetchedAt": "2026-03-27T17:46:12.542Z",
      "baselineMode": "previous_close",
      "baselineLabelJa": "前日終値",
      "baselineTimezone": "America/New_York",
      "baselineCutoverHourLocal": 17,
      "baselineCutoverMinuteLocal": 0,
      "baselineCutoverLabelJa": "06:00/07:00 JST",
      "baselinePrice": 9274.9,
      "change": 464.3,
      "changePercent": 5.006,
      "baselineSource": "snapshot-close",
      "baselineSnapshotDate": "2026-03-26",
      "baselineSnapshotCapturedAt": "2026-03-26T20:45:54.757Z"
    },
    {
      "id": "weekend-usdjpy",
      "marketId": "SUNUSDJPY",
      "name": "Weekend USDJPY",
      "url": "https://www.ig.com/en/indices/markets-indices/weekend-usdjpy",
      "bid": 160.253,
      "offer": 160.453,
      "currentPrice": 160.353,
      "high": 160.507,
      "low": 159.279,
      "stale": false,
      "fetchedAt": "2026-03-27T17:46:13.415Z",
      "baselineMode": "previous_close",
      "baselineLabelJa": "前日終値",
      "baselineTimezone": "America/New_York",
      "baselineCutoverHourLocal": 17,
      "baselineCutoverMinuteLocal": 0,
      "baselineCutoverLabelJa": "06:00/07:00 JST",
      "baselinePrice": 159.673,
      "change": 0.68,
      "changePercent": 0.4259,
      "baselineSource": "snapshot-close",
      "baselineSnapshotDate": "2026-03-26",
      "baselineSnapshotCapturedAt": "2026-03-26T20:45:54.757Z"
    },
    {
      "id": "weekend-eurusd",
      "marketId": "SUNEURUSD",
      "name": "Weekend EURUSD",
      "url": "https://www.ig.com/en/indices/markets-indices/weekend-eurusd",
      "bid": 1.1501,
      "offer": 1.1516,
      "currentPrice": 1.1508,
      "high": 1.1566,
      "low": 1.1494,
      "stale": false,
      "fetchedAt": "2026-03-27T17:46:13.112Z",
      "baselineMode": "previous_close",
      "baselineLabelJa": "前日終値",
      "baselineTimezone": "America/New_York",
      "baselineCutoverHourLocal": 17,
      "baselineCutoverMinuteLocal": 0,
      "baselineCutoverLabelJa": "06:00/07:00 JST",
      "baselinePrice": 1.1533,
      "change": -0.0025,
      "changePercent": -0.2168,
      "baselineSource": "snapshot-close",
      "baselineSnapshotDate": "2026-03-26",
      "baselineSnapshotCapturedAt": "2026-03-26T20:45:54.757Z"
    },
    {
      "id": "bitcoin-usd",
      "marketId": "BITCOIN",
      "name": "Bitcoin (USD)",
      "url": "https://www.ig.com/en/forex/markets-forex/bitcoin-1",
      "bid": 65871,
      "offer": 65916,
      "currentPrice": 65893.5,
      "high": 69241,
      "low": 65734,
      "stale": false,
      "fetchedAt": "2026-03-27T17:46:13.048Z",
      "baselineMode": "previous_close",
      "baselineLabelJa": "前日終値",
      "baselineTimezone": "America/New_York",
      "baselineCutoverHourLocal": 17,
      "baselineCutoverMinuteLocal": 0,
      "baselineCutoverLabelJa": "06:00/07:00 JST",
      "baselinePrice": 69180.5,
      "change": -3287,
      "changePercent": -4.7513,
      "baselineSource": "snapshot-close",
      "baselineSnapshotDate": "2026-03-26",
      "baselineSnapshotCapturedAt": "2026-03-26T20:45:54.757Z"
    },
    {
      "id": "ether-usd",
      "marketId": "ETHUSD",
      "name": "Ether (USD)",
      "url": "https://www.ig.com/en/forex/markets-forex/ether-usd",
      "bid": 1981.6,
      "offer": 1983,
      "currentPrice": 1982.3,
      "high": 2076.5,
      "low": 1970.4,
      "stale": false,
      "fetchedAt": "2026-03-27T17:46:13.326Z",
      "baselineMode": "previous_close",
      "baselineLabelJa": "前日終値",
      "baselineTimezone": "America/New_York",
      "baselineCutoverHourLocal": 17,
      "baselineCutoverMinuteLocal": 0,
      "baselineCutoverLabelJa": "06:00/07:00 JST",
      "baselinePrice": 2070.1,
      "change": -87.8,
      "changePercent": -4.2413,
      "baselineSource": "snapshot-close",
      "baselineSnapshotDate": "2026-03-26",
      "baselineSnapshotCapturedAt": "2026-03-26T20:45:54.757Z"
    },
    {
      "id": "crypto-10-index",
      "marketId": "CRYPTOB10",
      "name": "Crypto 10 Index",
      "url": "https://www.ig.com/en/forex/markets-forex/crypto-10-index",
      "bid": 13798.83,
      "offer": 13878.83,
      "currentPrice": 13838.83,
      "high": 14474.9,
      "low": 13794.6,
      "stale": false,
      "fetchedAt": "2026-03-27T17:46:13.212Z",
      "baselineMode": "previous_close",
      "baselineLabelJa": "前日終値",
      "baselineTimezone": "America/New_York",
      "baselineCutoverHourLocal": 17,
      "baselineCutoverMinuteLocal": 0,
      "baselineCutoverLabelJa": "06:00/07:00 JST",
      "baselinePrice": 14403.45,
      "change": -564.62,
      "changePercent": -3.92,
      "baselineSource": "snapshot-close",
      "baselineSnapshotDate": "2026-03-26",
      "baselineSnapshotCapturedAt": "2026-03-26T20:45:54.757Z"
    }
  ]
}
