{
  "updatedAt": "2026-06-08T11:15:45.424Z",
  "timezone": "Asia/Tokyo",
  "baselineMode": "previous_close",
  "baselineLabelJa": "前日終値",
  "source": "ig.com",
  "markets": [
    {
      "id": "weekend-us-tech-100-e1",
      "marketId": "SUNNAS",
      "name": "Weekend US Tech 100",
      "url": "https://www.ig.com/en/indices/markets-indices/weekend-us-tech-100-e1",
      "bid": 29168.9,
      "offer": 29208.9,
      "currentPrice": 29188.9,
      "high": 29264.5,
      "low": 28581.9,
      "stale": false,
      "fetchedAt": "2026-06-08T11:15:46.209Z",
      "baselineMode": "previous_close",
      "baselineLabelJa": "前日終値",
      "baselineTimezone": "America/New_York",
      "baselineCutoverHourLocal": 17,
      "baselineCutoverMinuteLocal": 0,
      "baselineCutoverLabelJa": "06:00/07:00 JST",
      "baselinePrice": 28769.6,
      "change": 419.3,
      "changePercent": 1.4574,
      "baselineSource": "snapshot-close",
      "baselineSnapshotDate": "2026-06-05",
      "baselineSnapshotCapturedAt": "2026-06-05T20:45:38.514Z"
    },
    {
      "id": "weekend-wall-street",
      "marketId": "SUNDOW",
      "name": "Weekend Wall Street",
      "url": "https://www.ig.com/en/indices/markets-indices/weekend-wall-street",
      "bid": 50825.8,
      "offer": 50880.8,
      "currentPrice": 50853.3,
      "high": 50931.1,
      "low": 50418.2,
      "stale": false,
      "fetchedAt": "2026-06-08T11:15:46.259Z",
      "baselineMode": "previous_close",
      "baselineLabelJa": "前日終値",
      "baselineTimezone": "America/New_York",
      "baselineCutoverHourLocal": 17,
      "baselineCutoverMinuteLocal": 0,
      "baselineCutoverLabelJa": "06:00/07:00 JST",
      "baselinePrice": 50701,
      "change": 152.3,
      "changePercent": 0.3004,
      "baselineSource": "snapshot-close",
      "baselineSnapshotDate": "2026-06-05",
      "baselineSnapshotCapturedAt": "2026-06-05T20:45:38.514Z"
    },
    {
      "id": "weekend-uk-100",
      "marketId": "SUNFUN",
      "name": "Weekend UK 100",
      "url": "https://www.ig.com/en/indices/markets-indices/weekend-uk-100",
      "bid": 10359.5,
      "offer": 10371.5,
      "currentPrice": 10365.5,
      "high": 10407.2,
      "low": 10270.6,
      "stale": false,
      "fetchedAt": "2026-06-08T11:15:46.279Z",
      "baselineMode": "previous_close",
      "baselineLabelJa": "前日終値",
      "baselineTimezone": "America/New_York",
      "baselineCutoverHourLocal": 17,
      "baselineCutoverMinuteLocal": 0,
      "baselineCutoverLabelJa": "06:00/07:00 JST",
      "baselinePrice": 10296.7,
      "change": 68.8,
      "changePercent": 0.6682,
      "baselineSource": "snapshot-close",
      "baselineSnapshotDate": "2026-06-05",
      "baselineSnapshotCapturedAt": "2026-06-05T20:45:38.514Z"
    },
    {
      "id": "weekend-germany-40",
      "marketId": "SUNDAX",
      "name": "Weekend Germany 40",
      "url": "https://www.ig.com/en/indices/markets-indices/weekend-germany-40",
      "bid": 24641.3,
      "offer": 24676.3,
      "currentPrice": 24658.8,
      "high": 24726.8,
      "low": 24279.7,
      "stale": false,
      "fetchedAt": "2026-06-08T11:15:46.248Z",
      "baselineMode": "previous_close",
      "baselineLabelJa": "前日終値",
      "baselineTimezone": "America/New_York",
      "baselineCutoverHourLocal": 17,
      "baselineCutoverMinuteLocal": 0,
      "baselineCutoverLabelJa": "06:00/07:00 JST",
      "baselinePrice": 24429.7,
      "change": 229.1,
      "changePercent": 0.9378,
      "baselineSource": "snapshot-close",
      "baselineSnapshotDate": "2026-06-05",
      "baselineSnapshotCapturedAt": "2026-06-05T20:45:38.514Z"
    },
    {
      "id": "weekend-hongkong-hs50",
      "marketId": "SUNHANS",
      "name": "Weekend Hong Kong HS50",
      "url": "https://www.ig.com/en/indices/markets-indices/weekend-hongkong-hs50",
      "bid": 24614.6,
      "offer": 24674.6,
      "currentPrice": 24644.6,
      "high": 24855.8,
      "low": 24351.1,
      "stale": false,
      "fetchedAt": "2026-06-08T11:15:46.237Z",
      "baselineMode": "previous_close",
      "baselineLabelJa": "前日終値",
      "baselineTimezone": "America/New_York",
      "baselineCutoverHourLocal": 17,
      "baselineCutoverMinuteLocal": 0,
      "baselineCutoverLabelJa": "06:00/07:00 JST",
      "baselinePrice": 24408.2,
      "change": 236.4,
      "changePercent": 0.9685,
      "baselineSource": "snapshot-close",
      "baselineSnapshotDate": "2026-06-05",
      "baselineSnapshotCapturedAt": "2026-06-05T20:45:38.514Z"
    },
    {
      "id": "weekend-australia-200",
      "marketId": "SUNASX",
      "name": "Weekend Australia 200",
      "url": "https://www.ig.com/en/indices/markets-indices/weekend-australia-200",
      "bid": 8541.9,
      "offer": 8551.9,
      "currentPrice": 8546.9,
      "high": 8555.1,
      "low": 8481.6,
      "stale": false,
      "fetchedAt": "2026-06-08T11:15:46.231Z",
      "baselineMode": "previous_close",
      "baselineLabelJa": "前日終値",
      "baselineTimezone": "America/New_York",
      "baselineCutoverHourLocal": 17,
      "baselineCutoverMinuteLocal": 0,
      "baselineCutoverLabelJa": "06:00/07:00 JST",
      "baselinePrice": 8490.1,
      "change": 56.8,
      "changePercent": 0.669,
      "baselineSource": "snapshot-close",
      "baselineSnapshotDate": "2026-06-05",
      "baselineSnapshotCapturedAt": "2026-06-05T20:45:38.514Z"
    },
    {
      "id": "weekend-gold",
      "marketId": "SUNGOLD",
      "name": "Weekend Gold",
      "url": "https://www.ig.com/en/indices/markets-indices/weekend-gold",
      "bid": 4305.9,
      "offer": 4310.9,
      "currentPrice": 4308.4,
      "high": 4356,
      "low": 4267,
      "stale": false,
      "fetchedAt": "2026-06-08T11:15:46.165Z",
      "baselineMode": "previous_close",
      "baselineLabelJa": "前日終値",
      "baselineTimezone": "America/New_York",
      "baselineCutoverHourLocal": 17,
      "baselineCutoverMinuteLocal": 0,
      "baselineCutoverLabelJa": "06:00/07:00 JST",
      "baselinePrice": 4322.5,
      "change": -14.1,
      "changePercent": -0.3262,
      "baselineSource": "snapshot-close",
      "baselineSnapshotDate": "2026-06-05",
      "baselineSnapshotCapturedAt": "2026-06-05T20:45:38.514Z"
    },
    {
      "id": "weekend-spot-silver",
      "marketId": "SUNSILVER",
      "name": "Weekend Spot Silver",
      "url": "https://www.ig.com/en/indices/markets-indices/weekend-spot-silver",
      "bid": 6728.4,
      "offer": 6753.4,
      "currentPrice": 6740.9,
      "high": 6862.1,
      "low": 6604.1,
      "stale": false,
      "fetchedAt": "2026-06-08T11:15:46.243Z",
      "baselineMode": "previous_close",
      "baselineLabelJa": "前日終値",
      "baselineTimezone": "America/New_York",
      "baselineCutoverHourLocal": 17,
      "baselineCutoverMinuteLocal": 0,
      "baselineCutoverLabelJa": "06:00/07:00 JST",
      "baselinePrice": 6764.3,
      "change": -23.4,
      "changePercent": -0.3459,
      "baselineSource": "snapshot-close",
      "baselineSnapshotDate": "2026-06-05",
      "baselineSnapshotCapturedAt": "2026-06-05T20:45:38.514Z"
    },
    {
      "id": "weekend-oil---us-crude",
      "marketId": "SUNCL",
      "name": "Weekend Oil - US Crude",
      "url": "https://www.ig.com/en/indices/markets-indices/weekend-oil---us-crude",
      "bid": 9207.7,
      "offer": 9277.7,
      "currentPrice": 9242.7,
      "high": 9564.7,
      "low": 8849,
      "stale": false,
      "fetchedAt": "2026-06-08T11:15:46.172Z",
      "baselineMode": "previous_close",
      "baselineLabelJa": "前日終値",
      "baselineTimezone": "America/New_York",
      "baselineCutoverHourLocal": 17,
      "baselineCutoverMinuteLocal": 0,
      "baselineCutoverLabelJa": "06:00/07:00 JST",
      "baselinePrice": 8898.6,
      "change": 344.1,
      "changePercent": 3.8669,
      "baselineSource": "snapshot-close",
      "baselineSnapshotDate": "2026-06-05",
      "baselineSnapshotCapturedAt": "2026-06-05T20:45:38.514Z"
    },
    {
      "id": "weekend-usdjpy",
      "marketId": "SUNUSDJPY",
      "name": "Weekend USDJPY",
      "url": "https://www.ig.com/en/indices/markets-indices/weekend-usdjpy",
      "bid": 159.888,
      "offer": 160.048,
      "currentPrice": 159.968,
      "high": 160.474,
      "low": 159.805,
      "stale": false,
      "fetchedAt": "2026-06-08T11:15:46.201Z",
      "baselineMode": "previous_close",
      "baselineLabelJa": "前日終値",
      "baselineTimezone": "America/New_York",
      "baselineCutoverHourLocal": 17,
      "baselineCutoverMinuteLocal": 0,
      "baselineCutoverLabelJa": "06:00/07:00 JST",
      "baselinePrice": 160.198,
      "change": -0.23,
      "changePercent": -0.1436,
      "baselineSource": "snapshot-close",
      "baselineSnapshotDate": "2026-06-05",
      "baselineSnapshotCapturedAt": "2026-06-05T20:45:38.514Z"
    },
    {
      "id": "weekend-eurusd",
      "marketId": "SUNEURUSD",
      "name": "Weekend EURUSD",
      "url": "https://www.ig.com/en/indices/markets-indices/weekend-eurusd",
      "bid": 1.1522,
      "offer": 1.1537,
      "currentPrice": 1.1529,
      "high": 1.1547,
      "low": 1.1492,
      "stale": false,
      "fetchedAt": "2026-06-08T11:15:46.220Z",
      "baselineMode": "previous_close",
      "baselineLabelJa": "前日終値",
      "baselineTimezone": "America/New_York",
      "baselineCutoverHourLocal": 17,
      "baselineCutoverMinuteLocal": 0,
      "baselineCutoverLabelJa": "06:00/07:00 JST",
      "baselinePrice": 1.1523,
      "change": 0.0006,
      "changePercent": 0.0521,
      "baselineSource": "snapshot-close",
      "baselineSnapshotDate": "2026-06-05",
      "baselineSnapshotCapturedAt": "2026-06-05T20:45:38.514Z"
    },
    {
      "id": "bitcoin-usd",
      "marketId": "BITCOIN",
      "name": "Bitcoin (USD)",
      "url": "https://www.ig.com/en/forex/markets-forex/bitcoin-1",
      "bid": 59398,
      "offer": 59443,
      "currentPrice": 59420.5,
      "high": 63997,
      "low": 59121,
      "stale": false,
      "fetchedAt": "2026-06-08T11:15:46.859Z",
      "baselineMode": "previous_close",
      "baselineLabelJa": "前日終値",
      "baselineTimezone": "America/New_York",
      "baselineCutoverHourLocal": 17,
      "baselineCutoverMinuteLocal": 0,
      "baselineCutoverLabelJa": "06:00/07:00 JST",
      "baselinePrice": 59420.5,
      "change": 0,
      "changePercent": 0,
      "baselineSource": "snapshot-close",
      "baselineSnapshotDate": "2026-06-05",
      "baselineSnapshotCapturedAt": "2026-06-05T20:45:38.514Z"
    },
    {
      "id": "ether-usd",
      "marketId": "ETHUSD",
      "name": "Ether (USD)",
      "url": "https://www.ig.com/en/forex/markets-forex/ether-usd",
      "bid": 1671.4,
      "offer": 1672.8,
      "currentPrice": 1672.1,
      "high": 1717.1,
      "low": 1622.9,
      "stale": false,
      "fetchedAt": "2026-06-08T11:15:46.254Z",
      "baselineMode": "previous_close",
      "baselineLabelJa": "前日終値",
      "baselineTimezone": "America/New_York",
      "baselineCutoverHourLocal": 17,
      "baselineCutoverMinuteLocal": 0,
      "baselineCutoverLabelJa": "06:00/07:00 JST",
      "baselinePrice": 1598.1,
      "change": 74,
      "changePercent": 4.6305,
      "baselineSource": "snapshot-close",
      "baselineSnapshotDate": "2026-06-05",
      "baselineSnapshotCapturedAt": "2026-06-05T20:45:38.514Z"
    },
    {
      "id": "crypto-10-index",
      "marketId": "CRYPTOB10",
      "name": "Crypto 10 Index",
      "url": "https://www.ig.com/en/forex/markets-forex/crypto-10-index",
      "bid": 12425.32,
      "offer": 12505.32,
      "currentPrice": 12465.32,
      "high": 12724,
      "low": 12192.9,
      "stale": false,
      "fetchedAt": "2026-06-08T11:15:46.795Z",
      "baselineMode": "previous_close",
      "baselineLabelJa": "前日終値",
      "baselineTimezone": "America/New_York",
      "baselineCutoverHourLocal": 17,
      "baselineCutoverMinuteLocal": 0,
      "baselineCutoverLabelJa": "06:00/07:00 JST",
      "baselinePrice": 12018.34,
      "change": 446.98,
      "changePercent": 3.7191,
      "baselineSource": "snapshot-close",
      "baselineSnapshotDate": "2026-06-05",
      "baselineSnapshotCapturedAt": "2026-06-05T20:45:38.514Z"
    }
  ]
}
