{
  "updatedAt": "2026-03-22T14:00:29.619Z",
  "timezone": "Asia/Tokyo",
  "baselineMode": "friday_close",
  "baselineLabelJa": "金曜終値",
  "source": "ig.com",
  "markets": [
    {
      "id": "weekend-us-tech-100-e1",
      "marketId": "SUNNAS",
      "name": "Weekend US Tech 100",
      "url": "https://www.ig.com/en/indices/markets-indices/weekend-us-tech-100-e1",
      "bid": 23863.6,
      "offer": 23898.6,
      "currentPrice": 23881.1,
      "high": 24189.1,
      "low": 23844,
      "stale": false,
      "fetchedAt": "2026-03-22T14:00:30.477Z",
      "baselineMode": "friday_close",
      "baselineLabelJa": "金曜終値",
      "baselineTimezone": "America/New_York",
      "baselineCutoverHourLocal": 17,
      "baselineCutoverMinuteLocal": 0,
      "baselineCutoverLabelJa": "06:00/07:00 JST",
      "baselinePrice": 23918.2,
      "change": -37.1,
      "changePercent": -0.1551,
      "baselineSource": "snapshot-close",
      "baselineSnapshotDate": "2026-03-20",
      "baselineSnapshotCapturedAt": "2026-03-20T20:45:47.403Z"
    },
    {
      "id": "weekend-wall-street",
      "marketId": "SUNDOW",
      "name": "Weekend Wall Street",
      "url": "https://www.ig.com/en/indices/markets-indices/weekend-wall-street",
      "bid": 45551.8,
      "offer": 45616.8,
      "currentPrice": 45584.3,
      "high": 46208.2,
      "low": 45530.5,
      "stale": false,
      "fetchedAt": "2026-03-22T14:00:30.520Z",
      "baselineMode": "friday_close",
      "baselineLabelJa": "金曜終値",
      "baselineTimezone": "America/New_York",
      "baselineCutoverHourLocal": 17,
      "baselineCutoverMinuteLocal": 0,
      "baselineCutoverLabelJa": "06:00/07:00 JST",
      "baselinePrice": 45754.2,
      "change": -169.9,
      "changePercent": -0.3713,
      "baselineSource": "snapshot-close",
      "baselineSnapshotDate": "2026-03-20",
      "baselineSnapshotCapturedAt": "2026-03-20T20:45:47.403Z"
    },
    {
      "id": "weekend-uk-100",
      "marketId": "SUNFUN",
      "name": "Weekend UK 100",
      "url": "https://www.ig.com/en/indices/markets-indices/weekend-uk-100",
      "bid": 9836.6,
      "offer": 9848.6,
      "currentPrice": 9842.6,
      "high": 9916.8,
      "low": 9804.3,
      "stale": false,
      "fetchedAt": "2026-03-22T14:00:31.189Z",
      "baselineMode": "friday_close",
      "baselineLabelJa": "金曜終値",
      "baselineTimezone": "America/New_York",
      "baselineCutoverHourLocal": 17,
      "baselineCutoverMinuteLocal": 0,
      "baselineCutoverLabelJa": "06:00/07:00 JST",
      "baselinePrice": 9845,
      "change": -2.4,
      "changePercent": -0.0244,
      "baselineSource": "snapshot-close",
      "baselineSnapshotDate": "2026-03-20",
      "baselineSnapshotCapturedAt": "2026-03-20T20:45:47.403Z"
    },
    {
      "id": "weekend-germany-40",
      "marketId": "SUNDAX",
      "name": "Weekend Germany 40",
      "url": "https://www.ig.com/en/indices/markets-indices/weekend-germany-40",
      "bid": 22119.4,
      "offer": 22154.4,
      "currentPrice": 22136.9,
      "high": 22465.6,
      "low": 22096.9,
      "stale": false,
      "fetchedAt": "2026-03-22T14:00:31.363Z",
      "baselineMode": "friday_close",
      "baselineLabelJa": "金曜終値",
      "baselineTimezone": "America/New_York",
      "baselineCutoverHourLocal": 17,
      "baselineCutoverMinuteLocal": 0,
      "baselineCutoverLabelJa": "06:00/07:00 JST",
      "baselinePrice": 22186.6,
      "change": -49.7,
      "changePercent": -0.224,
      "baselineSource": "snapshot-close",
      "baselineSnapshotDate": "2026-03-20",
      "baselineSnapshotCapturedAt": "2026-03-20T20:45:47.403Z"
    },
    {
      "id": "weekend-hongkong-hs50",
      "marketId": "SUNHANS",
      "name": "Weekend Hong Kong HS50",
      "url": "https://www.ig.com/en/indices/markets-indices/weekend-hongkong-hs50",
      "bid": 24723.8,
      "offer": 24783.8,
      "currentPrice": 24753.8,
      "high": 24932.8,
      "low": 24683.6,
      "stale": false,
      "fetchedAt": "2026-03-22T14:00:31.357Z",
      "baselineMode": "friday_close",
      "baselineLabelJa": "金曜終値",
      "baselineTimezone": "America/New_York",
      "baselineCutoverHourLocal": 17,
      "baselineCutoverMinuteLocal": 0,
      "baselineCutoverLabelJa": "06:00/07:00 JST",
      "baselinePrice": 24751.1,
      "change": 2.7,
      "changePercent": 0.0109,
      "baselineSource": "snapshot-close",
      "baselineSnapshotDate": "2026-03-20",
      "baselineSnapshotCapturedAt": "2026-03-20T20:45:47.403Z"
    },
    {
      "id": "weekend-australia-200",
      "marketId": "SUNASX",
      "name": "Weekend Australia 200",
      "url": "https://www.ig.com/en/indices/markets-indices/weekend-australia-200",
      "bid": 8280.2,
      "offer": 8290.2,
      "currentPrice": 8285.2,
      "high": 8371.8,
      "low": 8271.3,
      "stale": false,
      "fetchedAt": "2026-03-22T14:00:31.336Z",
      "baselineMode": "friday_close",
      "baselineLabelJa": "金曜終値",
      "baselineTimezone": "America/New_York",
      "baselineCutoverHourLocal": 17,
      "baselineCutoverMinuteLocal": 0,
      "baselineCutoverLabelJa": "06:00/07:00 JST",
      "baselinePrice": 8295.5,
      "change": -10.3,
      "changePercent": -0.1242,
      "baselineSource": "snapshot-close",
      "baselineSnapshotDate": "2026-03-20",
      "baselineSnapshotCapturedAt": "2026-03-20T20:45:47.403Z"
    },
    {
      "id": "weekend-gold",
      "marketId": "SUNGOLD",
      "name": "Weekend Gold",
      "url": "https://www.ig.com/en/indices/markets-indices/weekend-gold",
      "bid": 4485.1,
      "offer": 4500.1,
      "currentPrice": 4492.6,
      "high": 4547.9,
      "low": 4478.8,
      "stale": false,
      "fetchedAt": "2026-03-22T14:00:30.415Z",
      "baselineMode": "friday_close",
      "baselineLabelJa": "金曜終値",
      "baselineTimezone": "America/New_York",
      "baselineCutoverHourLocal": 17,
      "baselineCutoverMinuteLocal": 0,
      "baselineCutoverLabelJa": "06:00/07:00 JST",
      "baselinePrice": 4498.9,
      "change": -6.3,
      "changePercent": -0.14,
      "baselineSource": "snapshot-close",
      "baselineSnapshotDate": "2026-03-20",
      "baselineSnapshotCapturedAt": "2026-03-20T20:45:47.403Z"
    },
    {
      "id": "weekend-spot-silver",
      "marketId": "SUNSILVER",
      "name": "Weekend Spot Silver",
      "url": "https://www.ig.com/en/indices/markets-indices/weekend-spot-silver",
      "bid": 6772.7,
      "offer": 6797.7,
      "currentPrice": 6785.2,
      "high": 6899.1,
      "low": 6756.6,
      "stale": false,
      "fetchedAt": "2026-03-22T14:00:30.424Z",
      "baselineMode": "friday_close",
      "baselineLabelJa": "金曜終値",
      "baselineTimezone": "America/New_York",
      "baselineCutoverHourLocal": 17,
      "baselineCutoverMinuteLocal": 0,
      "baselineCutoverLabelJa": "06:00/07:00 JST",
      "baselinePrice": 6805.7,
      "change": -20.5,
      "changePercent": -0.3012,
      "baselineSource": "snapshot-close",
      "baselineSnapshotDate": "2026-03-20",
      "baselineSnapshotCapturedAt": "2026-03-20T20:45:47.403Z"
    },
    {
      "id": "weekend-oil---us-crude",
      "marketId": "SUNCL",
      "name": "Weekend Oil - US Crude",
      "url": "https://www.ig.com/en/indices/markets-indices/weekend-oil---us-crude",
      "bid": 9899.1,
      "offer": 9959.1,
      "currentPrice": 9929.1,
      "high": 10066.9,
      "low": 9559.7,
      "stale": false,
      "fetchedAt": "2026-03-22T14:00:30.640Z",
      "baselineMode": "friday_close",
      "baselineLabelJa": "金曜終値",
      "baselineTimezone": "America/New_York",
      "baselineCutoverHourLocal": 17,
      "baselineCutoverMinuteLocal": 0,
      "baselineCutoverLabelJa": "06:00/07:00 JST",
      "baselinePrice": 9765.7,
      "change": 163.4,
      "changePercent": 1.6732,
      "baselineSource": "snapshot-close",
      "baselineSnapshotDate": "2026-03-20",
      "baselineSnapshotCapturedAt": "2026-03-20T20:45:47.403Z"
    },
    {
      "id": "weekend-usdjpy",
      "marketId": "SUNUSDJPY",
      "name": "Weekend USDJPY",
      "url": "https://www.ig.com/en/indices/markets-indices/weekend-usdjpy",
      "bid": 159.076,
      "offer": 159.276,
      "currentPrice": 159.176,
      "high": 159.43,
      "low": 158.65,
      "stale": false,
      "fetchedAt": "2026-03-22T14:00:31.378Z",
      "baselineMode": "friday_close",
      "baselineLabelJa": "金曜終値",
      "baselineTimezone": "America/New_York",
      "baselineCutoverHourLocal": 17,
      "baselineCutoverMinuteLocal": 0,
      "baselineCutoverLabelJa": "06:00/07:00 JST",
      "baselinePrice": 159.305,
      "change": -0.129,
      "changePercent": -0.081,
      "baselineSource": "snapshot-close",
      "baselineSnapshotDate": "2026-03-20",
      "baselineSnapshotCapturedAt": "2026-03-20T20:45:47.403Z"
    },
    {
      "id": "weekend-eurusd",
      "marketId": "SUNEURUSD",
      "name": "Weekend EURUSD",
      "url": "https://www.ig.com/en/indices/markets-indices/weekend-eurusd",
      "bid": 1.1535,
      "offer": 1.155,
      "currentPrice": 1.1543,
      "high": 1.1593,
      "low": 1.1528,
      "stale": false,
      "fetchedAt": "2026-03-22T14:00:30.665Z",
      "baselineMode": "friday_close",
      "baselineLabelJa": "金曜終値",
      "baselineTimezone": "America/New_York",
      "baselineCutoverHourLocal": 17,
      "baselineCutoverMinuteLocal": 0,
      "baselineCutoverLabelJa": "06:00/07:00 JST",
      "baselinePrice": 1.1563,
      "change": -0.002,
      "changePercent": -0.173,
      "baselineSource": "snapshot-close",
      "baselineSnapshotDate": "2026-03-20",
      "baselineSnapshotCapturedAt": "2026-03-20T20:45:47.403Z"
    },
    {
      "id": "bitcoin-usd",
      "marketId": "BITCOIN",
      "name": "Bitcoin (USD)",
      "url": "https://www.ig.com/en/forex/markets-forex/bitcoin-1",
      "bid": 68675,
      "offer": 68720,
      "currentPrice": 68697.5,
      "high": 70565,
      "low": 68126,
      "stale": false,
      "fetchedAt": "2026-03-22T14:00:31.120Z",
      "baselineMode": "friday_close",
      "baselineLabelJa": "金曜終値",
      "baselineTimezone": "America/New_York",
      "baselineCutoverHourLocal": 17,
      "baselineCutoverMinuteLocal": 0,
      "baselineCutoverLabelJa": "06:00/07:00 JST",
      "baselinePrice": 69984.5,
      "change": -1287,
      "changePercent": -1.839,
      "baselineSource": "snapshot-close",
      "baselineSnapshotDate": "2026-03-20",
      "baselineSnapshotCapturedAt": "2026-03-20T20:45:47.403Z"
    },
    {
      "id": "ether-usd",
      "marketId": "ETHUSD",
      "name": "Ether (USD)",
      "url": "https://www.ig.com/en/forex/markets-forex/ether-usd",
      "bid": 2079.8,
      "offer": 2081.2,
      "currentPrice": 2080.5,
      "high": 2158,
      "low": 2050.9,
      "stale": false,
      "fetchedAt": "2026-03-22T14:00:31.657Z",
      "baselineMode": "friday_close",
      "baselineLabelJa": "金曜終値",
      "baselineTimezone": "America/New_York",
      "baselineCutoverHourLocal": 17,
      "baselineCutoverMinuteLocal": 0,
      "baselineCutoverLabelJa": "06:00/07:00 JST",
      "baselinePrice": 2128.8,
      "change": -48.3,
      "changePercent": -2.2689,
      "baselineSource": "snapshot-close",
      "baselineSnapshotDate": "2026-03-20",
      "baselineSnapshotCapturedAt": "2026-03-20T20:45:47.403Z"
    },
    {
      "id": "crypto-10-index",
      "marketId": "CRYPTOB10",
      "name": "Crypto 10 Index",
      "url": "https://www.ig.com/en/forex/markets-forex/crypto-10-index",
      "bid": 14434.56,
      "offer": 14514.56,
      "currentPrice": 14474.56,
      "high": 14904.6,
      "low": 14300.8,
      "stale": false,
      "fetchedAt": "2026-03-22T14:00:31.216Z",
      "baselineMode": "friday_close",
      "baselineLabelJa": "金曜終値",
      "baselineTimezone": "America/New_York",
      "baselineCutoverHourLocal": 17,
      "baselineCutoverMinuteLocal": 0,
      "baselineCutoverLabelJa": "06:00/07:00 JST",
      "baselinePrice": 14732.9,
      "change": -258.34,
      "changePercent": -1.7535,
      "baselineSource": "snapshot-close",
      "baselineSnapshotDate": "2026-03-20",
      "baselineSnapshotCapturedAt": "2026-03-20T20:45:47.403Z"
    }
  ]
}
